flask_structure_creator/__init__.py
flask_structure_creator/creator.py
flask_structure_creator-0.1.dist-info/LICENSE
flask_structure_creator-0.1.dist-info/METADATA
flask_structure_creator-0.1.dist-info/WHEEL
flask_structure_creator-0.1.dist-info/entry_points.txt
flask_structure_creator-0.1.dist-info/top_level.txt
flask_structure_creator-0.1.dist-info/RECORD
